{"metadata": {"dbt_schema_version": "https://schemas.getdbt.com/dbt/run-results/v4.json", "dbt_version": "1.0.4", "generated_at": "2022-07-12T18:03:48.424847Z", "invocation_id": "eec8b27b-eef3-4d29-a156-f9e977c057a5", "env": {}}, "results": [{"status": "success", "timing": [{"name": "compile", "started_at": "2022-07-12T18:03:46.915610Z", "completed_at": "2022-07-12T18:03:46.922648Z"}, {"name": "execute", "started_at": "2022-07-12T18:03:46.926472Z", "completed_at": "2022-07-12T18:03:46.926483Z"}], "thread_id": "Thread-1", "execution_time": 0.014077901840209961, "adapter_response": {}, "message": null, "failures": null, "unique_id": "seed.intercom_source_integration_tests.admin_data"}, {"status": "success", "timing": [{"name": "compile", "started_at": "2022-07-12T18:03:46.916044Z", "completed_at": "2022-07-12T18:03:46.925708Z"}, {"name": "execute", "started_at": "2022-07-12T18:03:46.926701Z", "completed_at": "2022-07-12T18:03:46.926705Z"}], "thread_id": "Thread-2", "execution_time": 0.013956785202026367, "adapter_response": {}, "message": null, "failures": null, "unique_id": "seed.intercom_source_integration_tests.company_history_data"}, {"status": "success", "timing": [{"name": "compile", "started_at": "2022-07-12T18:03:46.916207Z", "completed_at": "2022-07-12T18:03:46.925845Z"}, {"name": "execute", "started_at": "2022-07-12T18:03:46.926810Z", "completed_at": "2022-07-12T18:03:46.926814Z"}], "thread_id": "Thread-3", "execution_time": 0.013995170593261719, "adapter_response": {}, "message": null, "failures": null, "unique_id": "seed.intercom_source_integration_tests.company_tag_history_data"}, {"status": "success", "timing": [{"name": "compile", "started_at": "2022-07-12T18:03:46.918506Z", "completed_at": "2022-07-12T18:03:46.926124Z"}, {"name": "execute", "started_at": "2022-07-12T18:03:46.927241Z", "completed_at": "2022-07-12T18:03:46.927245Z"}], "thread_id": "Thread-4", "execution_time": 0.013641119003295898, "adapter_response": {}, "message": null, "failures": null, "unique_id": "seed.intercom_source_integration_tests.contact_company_history_data"}, {"status": "success", "timing": [{"name": "compile", "started_at": "2022-07-12T18:03:46.930606Z", "completed_at": "2022-07-12T18:03:46.952243Z"}, {"name": "execute", "started_at": "2022-07-12T18:03:46.989959Z", "completed_at": "2022-07-12T18:03:46.989975Z"}], "thread_id": "Thread-1", "execution_time": 0.061749935150146484, "adapter_response": {}, "message": null, "failures": null, "unique_id": "seed.intercom_source_integration_tests.contact_history_data"}, {"status": "success", "timing": [{"name": "compile", "started_at": "2022-07-12T18:03:46.930835Z", "completed_at": "2022-07-12T18:03:46.970468Z"}, {"name": "execute", "started_at": "2022-07-12T18:03:46.990321Z", "completed_at": "2022-07-12T18:03:46.990326Z"}], "thread_id": "Thread-2", "execution_time": 0.061602115631103516, "adapter_response": {}, "message": null, "failures": null, "unique_id": "seed.intercom_source_integration_tests.contact_tag_history_data"}, {"status": "success", "timing": [{"name": "compile", "started_at": "2022-07-12T18:03:46.930940Z", "completed_at": "2022-07-12T18:03:46.971097Z"}, {"name": "execute", "started_at": "2022-07-12T18:03:46.990456Z", "completed_at": "2022-07-12T18:03:46.990460Z"}], "thread_id": "Thread-3", "execution_time": 0.06156301498413086, "adapter_response": {}, "message": null, "failures": null, "unique_id": "seed.intercom_source_integration_tests.conversation_contact_history_data"}, {"status": "success", "timing": [{"name": "compile", "started_at": "2022-07-12T18:03:46.932705Z", "completed_at": "2022-07-12T18:03:46.971421Z"}, {"name": "execute", "started_at": "2022-07-12T18:03:46.990902Z", "completed_at": "2022-07-12T18:03:46.990906Z"}], "thread_id": "Thread-4", "execution_time": 0.06173992156982422, "adapter_response": {}, "message": null, "failures": null, "unique_id": "seed.intercom_source_integration_tests.conversation_history_data"}, {"status": "success", "timing": [{"name": "compile", "started_at": "2022-07-12T18:03:46.994336Z", "completed_at": "2022-07-12T18:03:47.049559Z"}, {"name": "execute", "started_at": "2022-07-12T18:03:47.068512Z", "completed_at": "2022-07-12T18:03:47.068520Z"}], "thread_id": "Thread-1", "execution_time": 0.07646012306213379, "adapter_response": {}, "message": null, "failures": null, "unique_id": "seed.intercom_source_integration_tests.conversation_part_history_data"}, {"status": "success", "timing": [{"name": "compile", "started_at": "2022-07-12T18:03:46.994673Z", "completed_at": "2022-07-12T18:03:47.067463Z"}, {"name": "execute", "started_at": "2022-07-12T18:03:47.068723Z", "completed_at": "2022-07-12T18:03:47.068726Z"}], "thread_id": "Thread-2", "execution_time": 0.07630801200866699, "adapter_response": {}, "message": null, "failures": null, "unique_id": "seed.intercom_source_integration_tests.conversation_tag_history_data"}, {"status": "success", "timing": [{"name": "compile", "started_at": "2022-07-12T18:03:46.994920Z", "completed_at": "2022-07-12T18:03:47.067882Z"}, {"name": "execute", "started_at": "2022-07-12T18:03:47.068823Z", "completed_at": "2022-07-12T18:03:47.068826Z"}], "thread_id": "Thread-3", "execution_time": 0.07630729675292969, "adapter_response": {}, "message": null, "failures": null, "unique_id": "seed.intercom_source_integration_tests.tag_data"}, {"status": "success", "timing": [{"name": "compile", "started_at": "2022-07-12T18:03:47.013503Z", "completed_at": "2022-07-12T18:03:47.068185Z"}, {"name": "execute", "started_at": "2022-07-12T18:03:47.069231Z", "completed_at": "2022-07-12T18:03:47.069234Z"}], "thread_id": "Thread-4", "execution_time": 0.0764150619506836, "adapter_response": {}, "message": null, "failures": null, "unique_id": "seed.intercom_source_integration_tests.team_admin_data"}, {"status": "success", "timing": [{"name": "compile", "started_at": "2022-07-12T18:03:47.072457Z", "completed_at": "2022-07-12T18:03:47.080287Z"}, {"name": "execute", "started_at": "2022-07-12T18:03:47.084266Z", "completed_at": "2022-07-12T18:03:47.084275Z"}], "thread_id": "Thread-1", "execution_time": 0.013871192932128906, "adapter_response": {}, "message": null, "failures": null, "unique_id": "seed.intercom_source_integration_tests.team_data"}, {"status": "success", "timing": [{"name": "compile", "started_at": "2022-07-12T18:03:47.072787Z", "completed_at": "2022-07-12T18:03:47.085559Z"}, {"name": "execute", "started_at": "2022-07-12T18:03:47.089687Z", "completed_at": "2022-07-12T18:03:47.089695Z"}], "thread_id": "Thread-3", "execution_time": 0.01863408088684082, "adapter_response": {}, "message": null, "failures": null, "unique_id": "model.intercom_source.stg_intercom__company_history_tmp"}, {"status": "success", "timing": [{"name": "compile", "started_at": "2022-07-12T18:03:47.072681Z", "completed_at": "2022-07-12T18:03:47.085719Z"}, {"name": "execute", "started_at": "2022-07-12T18:03:47.089832Z", "completed_at": "2022-07-12T18:03:47.089837Z"}], "thread_id": "Thread-2", "execution_time": 0.01921391487121582, "adapter_response": {}, "message": null, "failures": null, "unique_id": "model.intercom_source.stg_intercom__admin_tmp"}, {"status": "success", "timing": [{"name": "compile", "started_at": "2022-07-12T18:03:47.074429Z", "completed_at": "2022-07-12T18:03:47.085874Z"}, {"name": "execute", "started_at": "2022-07-12T18:03:47.089949Z", "completed_at": "2022-07-12T18:03:47.089953Z"}], "thread_id": "Thread-4", "execution_time": 0.0187680721282959, "adapter_response": {}, "message": null, "failures": null, "unique_id": "model.intercom_source.stg_intercom__company_tag_history_tmp"}, {"status": "success", "timing": [{"name": "compile", "started_at": "2022-07-12T18:03:47.086008Z", "completed_at": "2022-07-12T18:03:47.090973Z"}, {"name": "execute", "started_at": "2022-07-12T18:03:47.092464Z", "completed_at": "2022-07-12T18:03:47.092469Z"}], "thread_id": "Thread-1", "execution_time": 0.007912874221801758, "adapter_response": {}, "message": null, "failures": null, "unique_id": "model.intercom_source.stg_intercom__contact_company_history_tmp"}, {"status": "success", "timing": [{"name": "compile", "started_at": "2022-07-12T18:03:47.092777Z", "completed_at": "2022-07-12T18:03:47.102304Z"}, {"name": "execute", "started_at": "2022-07-12T18:03:47.105320Z", "completed_at": "2022-07-12T18:03:47.105327Z"}], "thread_id": "Thread-3", "execution_time": 0.01413106918334961, "adapter_response": {}, "message": null, "failures": null, "unique_id": "model.intercom_source.stg_intercom__contact_history_tmp"}, {"status": "success", "timing": [{"name": "compile", "started_at": "2022-07-12T18:03:47.093101Z", "completed_at": "2022-07-12T18:03:47.102418Z"}, {"name": "execute", "started_at": "2022-07-12T18:03:47.105425Z", "completed_at": "2022-07-12T18:03:47.105429Z"}], "thread_id": "Thread-2", "execution_time": 0.014047861099243164, "adapter_response": {}, "message": null, "failures": null, "unique_id": "model.intercom_source.stg_intercom__contact_tag_history_tmp"}, {"status": "success", "timing": [{"name": "compile", "started_at": "2022-07-12T18:03:47.093200Z", "completed_at": "2022-07-12T18:03:47.102612Z"}, {"name": "execute", "started_at": "2022-07-12T18:03:47.105563Z", "completed_at": "2022-07-12T18:03:47.105566Z"}], "thread_id": "Thread-4", "execution_time": 0.014097929000854492, "adapter_response": {}, "message": null, "failures": null, "unique_id": "model.intercom_source.stg_intercom__conversation_contact_history_tmp"}, {"status": "success", "timing": [{"name": "compile", "started_at": "2022-07-12T18:03:47.102528Z", "completed_at": "2022-07-12T18:03:47.106074Z"}, {"name": "execute", "started_at": "2022-07-12T18:03:47.107395Z", "completed_at": "2022-07-12T18:03:47.107399Z"}], "thread_id": "Thread-1", "execution_time": 0.0060901641845703125, "adapter_response": {}, "message": null, "failures": null, "unique_id": "model.intercom_source.stg_intercom__conversation_history_tmp"}, {"status": "success", "timing": [{"name": "compile", "started_at": "2022-07-12T18:03:47.108204Z", "completed_at": "2022-07-12T18:03:47.115019Z"}, {"name": "execute", "started_at": "2022-07-12T18:03:47.118789Z", "completed_at": "2022-07-12T18:03:47.118795Z"}], "thread_id": "Thread-2", "execution_time": 0.012008905410766602, "adapter_response": {}, "message": null, "failures": null, "unique_id": "model.intercom_source.stg_intercom__conversation_tag_history_tmp"}, {"status": "success", "timing": [{"name": "compile", "started_at": "2022-07-12T18:03:47.108117Z", "completed_at": "2022-07-12T18:03:47.115120Z"}, {"name": "execute", "started_at": "2022-07-12T18:03:47.118980Z", "completed_at": "2022-07-12T18:03:47.118984Z"}], "thread_id": "Thread-3", "execution_time": 0.01251673698425293, "adapter_response": {}, "message": null, "failures": null, "unique_id": "model.intercom_source.stg_intercom__conversation_part_history_tmp"}, {"status": "success", "timing": [{"name": "compile", "started_at": "2022-07-12T18:03:47.108481Z", "completed_at": "2022-07-12T18:03:47.115388Z"}, {"name": "execute", "started_at": "2022-07-12T18:03:47.119312Z", "completed_at": "2022-07-12T18:03:47.119317Z"}], "thread_id": "Thread-4", "execution_time": 0.01242971420288086, "adapter_response": {}, "message": null, "failures": null, "unique_id": "model.intercom_source.stg_intercom__tag_tmp"}, {"status": "success", "timing": [{"name": "compile", "started_at": "2022-07-12T18:03:47.115216Z", "completed_at": "2022-07-12T18:03:47.119757Z"}, {"name": "execute", "started_at": "2022-07-12T18:03:47.120845Z", "completed_at": "2022-07-12T18:03:47.120850Z"}], "thread_id": "Thread-1", "execution_time": 0.008573293685913086, "adapter_response": {}, "message": null, "failures": null, "unique_id": "model.intercom_source.stg_intercom__team_admin_tmp"}, {"status": "success", "timing": [{"name": "compile", "started_at": "2022-07-12T18:03:47.121132Z", "completed_at": "2022-07-12T18:03:47.134100Z"}, {"name": "execute", "started_at": "2022-07-12T18:03:47.138383Z", "completed_at": "2022-07-12T18:03:47.138388Z"}], "thread_id": "Thread-2", "execution_time": 0.018393754959106445, "adapter_response": {}, "message": null, "failures": null, "unique_id": "model.intercom_source.stg_intercom__team_tmp"}, {"status": "success", "timing": [{"name": "compile", "started_at": "2022-07-12T18:03:47.123868Z", "completed_at": "2022-07-12T18:03:47.440427Z"}, {"name": "execute", "started_at": "2022-07-12T18:03:47.443818Z", "completed_at": "2022-07-12T18:03:47.443823Z"}], "thread_id": "Thread-4", "execution_time": 0.35129404067993164, "adapter_response": {}, "message": null, "failures": null, "unique_id": "model.intercom_source.stg_intercom__admin"}, {"status": "success", "timing": [{"name": "compile", "started_at": "2022-07-12T18:03:47.121435Z", "completed_at": "2022-07-12T18:03:47.444173Z"}, {"name": "execute", "started_at": "2022-07-12T18:03:47.444730Z", "completed_at": "2022-07-12T18:03:47.444733Z"}], "thread_id": "Thread-3", "execution_time": 0.35184192657470703, "adapter_response": {}, "message": null, "failures": null, "unique_id": "model.intercom_source.stg_intercom__company_history"}, {"status": "success", "timing": [{"name": "compile", "started_at": "2022-07-12T18:03:47.139151Z", "completed_at": "2022-07-12T18:03:47.440290Z"}, {"name": "execute", "started_at": "2022-07-12T18:03:47.443708Z", "completed_at": "2022-07-12T18:03:47.443719Z"}], "thread_id": "Thread-2", "execution_time": 0.33366894721984863, "adapter_response": {}, "message": null, "failures": null, "unique_id": "model.intercom_source.stg_intercom__contact_company_history"}, {"status": "success", "timing": [{"name": "compile", "started_at": "2022-07-12T18:03:47.134249Z", "completed_at": "2022-07-12T18:03:47.443558Z"}, {"name": "execute", "started_at": "2022-07-12T18:03:47.444371Z", "completed_at": "2022-07-12T18:03:47.444374Z"}], "thread_id": "Thread-1", "execution_time": 0.34203481674194336, "adapter_response": {}, "message": null, "failures": null, "unique_id": "model.intercom_source.stg_intercom__company_tag_history"}, {"status": "success", "timing": [{"name": "compile", "started_at": "2022-07-12T18:03:47.475153Z", "completed_at": "2022-07-12T18:03:47.782576Z"}, {"name": "execute", "started_at": "2022-07-12T18:03:47.782993Z", "completed_at": "2022-07-12T18:03:47.783001Z"}], "thread_id": "Thread-2", "execution_time": 0.33528900146484375, "adapter_response": {}, "message": null, "failures": null, "unique_id": "model.intercom_source.stg_intercom__conversation_contact_history"}, {"status": "success", "timing": [{"name": "compile", "started_at": "2022-07-12T18:03:47.475080Z", "completed_at": "2022-07-12T18:03:47.785619Z"}, {"name": "execute", "started_at": "2022-07-12T18:03:47.785817Z", "completed_at": "2022-07-12T18:03:47.785821Z"}], "thread_id": "Thread-3", "execution_time": 0.33567118644714355, "adapter_response": {}, "message": null, "failures": null, "unique_id": "model.intercom_source.stg_intercom__contact_tag_history"}, {"status": "success", "timing": [{"name": "compile", "started_at": "2022-07-12T18:03:47.474916Z", "completed_at": "2022-07-12T18:03:47.797473Z"}, {"name": "execute", "started_at": "2022-07-12T18:03:47.797618Z", "completed_at": "2022-07-12T18:03:47.797621Z"}], "thread_id": "Thread-4", "execution_time": 0.34821200370788574, "adapter_response": {}, "message": null, "failures": null, "unique_id": "model.intercom_source.stg_intercom__contact_history"}, {"status": "success", "timing": [{"name": "compile", "started_at": "2022-07-12T18:03:47.481594Z", "completed_at": "2022-07-12T18:03:47.795453Z"}, {"name": "execute", "started_at": "2022-07-12T18:03:47.797177Z", "completed_at": "2022-07-12T18:03:47.797182Z"}], "thread_id": "Thread-1", "execution_time": 0.35152530670166016, "adapter_response": {}, "message": null, "failures": null, "unique_id": "model.intercom_source.stg_intercom__conversation_history"}, {"status": "success", "timing": [{"name": "compile", "started_at": "2022-07-12T18:03:47.811328Z", "completed_at": "2022-07-12T18:03:48.079642Z"}, {"name": "execute", "started_at": "2022-07-12T18:03:48.080045Z", "completed_at": "2022-07-12T18:03:48.080056Z"}], "thread_id": "Thread-3", "execution_time": 0.299713134765625, "adapter_response": {}, "message": null, "failures": null, "unique_id": "model.intercom_source.stg_intercom__conversation_part_history"}, {"status": "success", "timing": [{"name": "compile", "started_at": "2022-07-12T18:03:47.826427Z", "completed_at": "2022-07-12T18:03:48.090712Z"}, {"name": "execute", "started_at": "2022-07-12T18:03:48.095380Z", "completed_at": "2022-07-12T18:03:48.095389Z"}], "thread_id": "Thread-1", "execution_time": 0.29906296730041504, "adapter_response": {}, "message": null, "failures": null, "unique_id": "model.intercom_source.stg_intercom__team_admin"}, {"status": "success", "timing": [{"name": "compile", "started_at": "2022-07-12T18:03:47.822270Z", "completed_at": "2022-07-12T18:03:48.101819Z"}, {"name": "execute", "started_at": "2022-07-12T18:03:48.102073Z", "completed_at": "2022-07-12T18:03:48.102079Z"}], "thread_id": "Thread-4", "execution_time": 0.31126999855041504, "adapter_response": {}, "message": null, "failures": null, "unique_id": "model.intercom_source.stg_intercom__tag"}, {"status": "success", "timing": [{"name": "compile", "started_at": "2022-07-12T18:03:47.811232Z", "completed_at": "2022-07-12T18:03:48.102311Z"}, {"name": "execute", "started_at": "2022-07-12T18:03:48.102541Z", "completed_at": "2022-07-12T18:03:48.102544Z"}], "thread_id": "Thread-2", "execution_time": 0.32355785369873047, "adapter_response": {}, "message": null, "failures": null, "unique_id": "model.intercom_source.stg_intercom__conversation_tag_history"}, {"status": "success", "timing": [{"name": "compile", "started_at": "2022-07-12T18:03:48.125772Z", "completed_at": "2022-07-12T18:03:48.133984Z"}, {"name": "execute", "started_at": "2022-07-12T18:03:48.134713Z", "completed_at": "2022-07-12T18:03:48.134718Z"}], "thread_id": "Thread-1", "execution_time": 0.013602733612060547, "adapter_response": {}, "message": null, "failures": null, "unique_id": "test.intercom_source.not_null_stg_intercom__admin_admin_id.8630313ad7"}, {"status": "success", "timing": [{"name": "compile", "started_at": "2022-07-12T18:03:48.134464Z", "completed_at": "2022-07-12T18:03:48.142198Z"}, {"name": "execute", "started_at": "2022-07-12T18:03:48.142672Z", "completed_at": "2022-07-12T18:03:48.142677Z"}], "thread_id": "Thread-4", "execution_time": 0.012185096740722656, "adapter_response": {}, "message": null, "failures": null, "unique_id": "test.intercom_source.unique_stg_intercom__admin_admin_id.10ac4663c1"}, {"status": "success", "timing": [{"name": "compile", "started_at": "2022-07-12T18:03:48.139276Z", "completed_at": "2022-07-12T18:03:48.142588Z"}, {"name": "execute", "started_at": "2022-07-12T18:03:48.145972Z", "completed_at": "2022-07-12T18:03:48.145975Z"}], "thread_id": "Thread-2", "execution_time": 0.011743307113647461, "adapter_response": {}, "message": null, "failures": null, "unique_id": "test.intercom_source.not_null_stg_intercom__company_history_company_id.29e68d8641"}, {"status": "success", "timing": [{"name": "compile", "started_at": "2022-07-12T18:03:48.142516Z", "completed_at": "2022-07-12T18:03:48.146374Z"}, {"name": "execute", "started_at": "2022-07-12T18:03:48.169424Z", "completed_at": "2022-07-12T18:03:48.169429Z"}], "thread_id": "Thread-1", "execution_time": 0.02762317657470703, "adapter_response": {}, "message": null, "failures": null, "unique_id": "test.intercom_source.unique_stg_intercom__company_history_company_id.5978446e98"}, {"status": "success", "timing": [{"name": "compile", "started_at": "2022-07-12T18:03:48.169494Z", "completed_at": "2022-07-12T18:03:48.174078Z"}, {"name": "execute", "started_at": "2022-07-12T18:03:48.174500Z", "completed_at": "2022-07-12T18:03:48.174505Z"}], "thread_id": "Thread-4", "execution_time": 0.0301969051361084, "adapter_response": {}, "message": null, "failures": null, "unique_id": "test.intercom_source.not_null_stg_intercom__contact_company_history_company_id.ba3e617037"}, {"status": "success", "timing": [{"name": "compile", "started_at": "2022-07-12T18:03:48.171813Z", "completed_at": "2022-07-12T18:03:48.174310Z"}, {"name": "execute", "started_at": "2022-07-12T18:03:48.176750Z", "completed_at": "2022-07-12T18:03:48.176754Z"}], "thread_id": "Thread-2", "execution_time": 0.0077970027923583984, "adapter_response": {}, "message": null, "failures": null, "unique_id": "test.intercom_source.not_null_stg_intercom__contact_company_history_contact_id.5e389a0d84"}, {"status": "success", "timing": [{"name": "compile", "started_at": "2022-07-12T18:03:48.174369Z", "completed_at": "2022-07-12T18:03:48.177290Z"}, {"name": "execute", "started_at": "2022-07-12T18:03:48.177817Z", "completed_at": "2022-07-12T18:03:48.177820Z"}], "thread_id": "Thread-1", "execution_time": 0.006062746047973633, "adapter_response": {}, "message": null, "failures": null, "unique_id": "test.intercom_source.not_null_stg_intercom__company_tag_history_company_id.7ce26b3077"}, {"status": "success", "timing": [{"name": "compile", "started_at": "2022-07-12T18:03:48.177745Z", "completed_at": "2022-07-12T18:03:48.182273Z"}, {"name": "execute", "started_at": "2022-07-12T18:03:48.182679Z", "completed_at": "2022-07-12T18:03:48.182683Z"}], "thread_id": "Thread-4", "execution_time": 0.0077822208404541016, "adapter_response": {}, "message": null, "failures": null, "unique_id": "test.intercom_source.not_null_stg_intercom__company_tag_history_tag_id.a71b043180"}, {"status": "success", "timing": [{"name": "compile", "started_at": "2022-07-12T18:03:48.179976Z", "completed_at": "2022-07-12T18:03:48.182610Z"}, {"name": "execute", "started_at": "2022-07-12T18:03:48.185080Z", "completed_at": "2022-07-12T18:03:48.185084Z"}], "thread_id": "Thread-2", "execution_time": 0.007737874984741211, "adapter_response": {}, "message": null, "failures": null, "unique_id": "test.intercom_source.not_null_stg_intercom__conversation_contact_history_contact_id.faa2dd69f0"}, {"status": "success", "timing": [{"name": "compile", "started_at": "2022-07-12T18:03:48.182557Z", "completed_at": "2022-07-12T18:03:48.185421Z"}, {"name": "execute", "started_at": "2022-07-12T18:03:48.185955Z", "completed_at": "2022-07-12T18:03:48.185958Z"}], "thread_id": "Thread-1", "execution_time": 0.004051923751831055, "adapter_response": {}, "message": null, "failures": null, "unique_id": "test.intercom_source.not_null_stg_intercom__conversation_contact_history_conversation_id.6619b609cf"}, {"status": "success", "timing": [{"name": "compile", "started_at": "2022-07-12T18:03:48.186022Z", "completed_at": "2022-07-12T18:03:48.191027Z"}, {"name": "execute", "started_at": "2022-07-12T18:03:48.191393Z", "completed_at": "2022-07-12T18:03:48.191397Z"}], "thread_id": "Thread-4", "execution_time": 0.007798194885253906, "adapter_response": {}, "message": null, "failures": null, "unique_id": "test.intercom_source.not_null_stg_intercom__contact_tag_history_contact_id.80f3693f49"}, {"status": "success", "timing": [{"name": "compile", "started_at": "2022-07-12T18:03:48.188880Z", "completed_at": "2022-07-12T18:03:48.191247Z"}, {"name": "execute", "started_at": "2022-07-12T18:03:48.193374Z", "completed_at": "2022-07-12T18:03:48.193377Z"}], "thread_id": "Thread-2", "execution_time": 0.00781702995300293, "adapter_response": {}, "message": null, "failures": null, "unique_id": "test.intercom_source.not_null_stg_intercom__contact_tag_history_tag_id.24a4c9df63"}, {"status": "success", "timing": [{"name": "compile", "started_at": "2022-07-12T18:03:48.191323Z", "completed_at": "2022-07-12T18:03:48.193762Z"}, {"name": "execute", "started_at": "2022-07-12T18:03:48.194344Z", "completed_at": "2022-07-12T18:03:48.194347Z"}], "thread_id": "Thread-1", "execution_time": 0.003713846206665039, "adapter_response": {}, "message": null, "failures": null, "unique_id": "test.intercom_source.not_null_stg_intercom__contact_history_contact_id.433f831acf"}, {"status": "success", "timing": [{"name": "compile", "started_at": "2022-07-12T18:03:48.194411Z", "completed_at": "2022-07-12T18:03:48.198755Z"}, {"name": "execute", "started_at": "2022-07-12T18:03:48.200859Z", "completed_at": "2022-07-12T18:03:48.200864Z"}], "thread_id": "Thread-4", "execution_time": 0.007304191589355469, "adapter_response": {}, "message": null, "failures": null, "unique_id": "test.intercom_source.not_null_stg_intercom__conversation_history_conversation_id.947be5d87e"}, {"status": "success", "timing": [{"name": "compile", "started_at": "2022-07-12T18:03:48.196411Z", "completed_at": "2022-07-12T18:03:48.200782Z"}, {"name": "execute", "started_at": "2022-07-12T18:03:48.201208Z", "completed_at": "2022-07-12T18:03:48.201211Z"}], "thread_id": "Thread-2", "execution_time": 0.007330179214477539, "adapter_response": {}, "message": null, "failures": null, "unique_id": "test.intercom_source.not_null_stg_intercom__conversation_part_history_conversation_part_id.53df1b68d4"}, {"status": "success", "timing": [{"name": "compile", "started_at": "2022-07-12T18:03:48.198846Z", "completed_at": "2022-07-12T18:03:48.201265Z"}, {"name": "execute", "started_at": "2022-07-12T18:03:48.201839Z", "completed_at": "2022-07-12T18:03:48.201841Z"}], "thread_id": "Thread-1", "execution_time": 0.003618001937866211, "adapter_response": {}, "message": null, "failures": null, "unique_id": "test.intercom_source.not_null_stg_intercom__team_admin_team_id.11bddbf17b"}, {"status": "success", "timing": [{"name": "compile", "started_at": "2022-07-12T18:03:48.202197Z", "completed_at": "2022-07-12T18:03:48.206875Z"}, {"name": "execute", "started_at": "2022-07-12T18:03:48.207141Z", "completed_at": "2022-07-12T18:03:48.207145Z"}], "thread_id": "Thread-4", "execution_time": 0.0057718753814697266, "adapter_response": {}, "message": null, "failures": null, "unique_id": "test.intercom_source.not_null_stg_intercom__conversation_tag_history_conversation_id.2b897a1922"}, {"status": "success", "timing": [{"name": "compile", "started_at": "2022-07-12T18:03:48.204847Z", "completed_at": "2022-07-12T18:03:48.207056Z"}, {"name": "execute", "started_at": "2022-07-12T18:03:48.207505Z", "completed_at": "2022-07-12T18:03:48.207508Z"}], "thread_id": "Thread-2", "execution_time": 0.0057680606842041016, "adapter_response": {}, "message": null, "failures": null, "unique_id": "test.intercom_source.not_null_stg_intercom__conversation_tag_history_tag_id.11ffc3e16e"}, {"status": "success", "timing": [{"name": "compile", "started_at": "2022-07-12T18:03:48.111277Z", "completed_at": "2022-07-12T18:03:48.381552Z"}, {"name": "execute", "started_at": "2022-07-12T18:03:48.381879Z", "completed_at": "2022-07-12T18:03:48.381894Z"}], "thread_id": "Thread-3", "execution_time": 0.29918885231018066, "adapter_response": {}, "message": null, "failures": null, "unique_id": "model.intercom_source.stg_intercom__team"}, {"status": "success", "timing": [{"name": "compile", "started_at": "2022-07-12T18:03:48.412360Z", "completed_at": "2022-07-12T18:03:48.421726Z"}, {"name": "execute", "started_at": "2022-07-12T18:03:48.422197Z", "completed_at": "2022-07-12T18:03:48.422210Z"}], "thread_id": "Thread-4", "execution_time": 0.011176109313964844, "adapter_response": {}, "message": null, "failures": null, "unique_id": "test.intercom_source.unique_stg_intercom__team_team_id.41ec840e13"}, {"status": "success", "timing": [{"name": "compile", "started_at": "2022-07-12T18:03:48.412214Z", "completed_at": "2022-07-12T18:03:48.422050Z"}, {"name": "execute", "started_at": "2022-07-12T18:03:48.423089Z", "completed_at": "2022-07-12T18:03:48.423095Z"}], "thread_id": "Thread-1", "execution_time": 0.01218724250793457, "adapter_response": {}, "message": null, "failures": null, "unique_id": "test.intercom_source.not_null_stg_intercom__team_team_id.f6f47bb6ae"}], "elapsed_time": 3.832664966583252, "args": {"write_json": true, "use_colors": true, "printer_width": 80, "version_check": true, "partial_parse": true, "static_parser": true, "profiles_dir": "/Users/joseph.markiewicz/.dbt", "send_anonymous_usage_stats": true, "event_buffer_size": 100000, "target": "postgres", "compile": true, "which": "generate", "rpc_method": "docs.generate", "indirect_selection": "eager"}}